matinverse/IO.py
matinverse/__init__.py
matinverse/boundary_conditions.py
matinverse/fields.py
matinverse/filtering.py
matinverse/fourier.py
matinverse/geometry2D.py
matinverse/geometry3D.py
matinverse/inequalities.py
matinverse/optimizer.py
matinverse/projection.py
matinverse/sparse.py
matinverse/symmetry.py
matinverse/visualizer.py
matinverse-1.0.7.dist-info/licenses/LICENSE
matinverse-1.0.7.dist-info/METADATA
matinverse-1.0.7.dist-info/WHEEL
matinverse-1.0.7.dist-info/top_level.txt
matinverse-1.0.7.dist-info/RECORD
